fastbnns/__init__.py
fastbnns/analysis/__init__.py
fastbnns/analysis/statistics.py
fastbnns/bnn/__init__.py
fastbnns/bnn/base.py
fastbnns/bnn/inference.py
fastbnns/bnn/losses.py
fastbnns/bnn/priors.py
fastbnns/bnn/types.py
fastbnns/bnn/wrappers.py
fastbnns/datasets/__init__.py
fastbnns/datasets/generic.py
fastbnns/datasets/polynomial.py
fastbnns/models/__init__.py
fastbnns/models/activations.py
fastbnns/models/cnn.py
fastbnns/models/lightning_wrappers.py
fastbnns/models/mlp.py
fastbnns/models/polynomial.py
fastbnns/simulation/__init__.py
fastbnns/simulation/generators.py
fastbnns/simulation/images.py
fastbnns/simulation/observation.py
fastbnns/simulation/polynomials.py
fastbnns/utils/__init__.py
fastbnns/utils/torch_utils.py
fastbnns-0.2.3.dist-info/licenses/LICENSE.md
fastbnns-0.2.3.dist-info/METADATA
fastbnns-0.2.3.dist-info/WHEEL
fastbnns-0.2.3.dist-info/top_level.txt
fastbnns-0.2.3.dist-info/RECORD
