Metadata-Version: 2.4
Name: fastbnns
Version: 0.2.3
Summary: Fast training and inference for Bayesian neural networks.
Author-email: "David J. Schodt" <dschodt@lanl.gov>
License-Expression: BSD-3-Clause
Project-URL: Homepage, https://github.com/lanl/FastBNNs
Project-URL: Repository, https://github.com/lanl/FastBNNs
Project-URL: Issues, https://github.com/lanl/FastBNNs/issues
Requires-Python: <3.13,>=3.10
License-File: LICENSE.md
Requires-Dist: scipy
Provides-Extra: plot
Requires-Dist: matplotlib; extra == "plot"
Provides-Extra: examples
Requires-Dist: lightning; extra == "examples"
Dynamic: license-file
